CMakeLists.txt
MANIFEST.in
README.md
setup.py
core/CMakeLists.txt
core/apriltag.c
core/apriltag.h
core/apriltag_demo.c
core/apriltag_family.c
core/apriltag_family.h
core/apriltag_quad_thresh.c
core/g2d.c
core/g2d.h
core/tag16h5.c
core/tag16h5.h
core/tag25h7.c
core/tag25h7.h
core/tag25h9.c
core/tag25h9.h
core/tag36artoolkit.c
core/tag36artoolkit.h
core/tag36h10.c
core/tag36h10.h
core/tag36h11.c
core/tag36h11.h
core/common/assert_with_unused.h
core/common/getopt.c
core/common/getopt.h
core/common/homography.c
core/common/homography.h
core/common/image_f32.c
core/common/image_f32.h
core/common/image_u32.c
core/common/image_u32.h
core/common/image_u8.c
core/common/image_u8.h
core/common/matd.c
core/common/matd.h
core/common/math_util.h
core/common/pnm.c
core/common/pnm.h
core/common/postscript_utils.h
core/common/string_util.c
core/common/string_util.h
core/common/svd22.c
core/common/svd22.h
core/common/thash_impl.h
core/common/time_util.c
core/common/time_util.h
core/common/timeprofile.h
core/common/unionfind.c
core/common/unionfind.h
core/common/workerpool.c
core/common/workerpool.h
core/common/zarray.c
core/common/zarray.h
core/common/zhash.c
core/common/zhash.h
core/common/zmaxheap.c
core/common/zmaxheap.h
core/contrib/apriltag_quad_contour.c
core/contrib/apriltag_quad_contour.h
core/contrib/apriltag_vis.c
core/contrib/apriltag_vis.h
core/contrib/box.c
core/contrib/box.h
core/contrib/contour.c
core/contrib/contour.h
core/contrib/contour_test.c
core/contrib/lm.c
core/contrib/lm.h
core/contrib/lm_test.cpp
core/contrib/pdf_test.cpp
core/contrib/pdfutil.c
core/contrib/pdfutil.h
images/fat_tags.png
images/clipboard/clipboard00.png
images/clipboard/clipboard01.png
images/clipboard/clipboard02.png
images/clipboard/clipboard03.png
images/clipboard/clipboard04.png
images/clipboard/clipboard05.png
images/clipboard/clipboard06.png
images/clipboard/clipboard07.png
images/clipboard/clipboard08.png
images/clipboard/clipboard09.png
images/hallway/IMG_0612.jpg
python/apriltags.egg-info/PKG-INFO
python/apriltags.egg-info/SOURCES.txt
python/apriltags.egg-info/dependency_links.txt
python/apriltags.egg-info/not-zip-safe
python/apriltags.egg-info/top_level.txt